perception/__init__.py
perception/camera_sensor.py
perception/colorized_phoxi_sensor.py
perception/ensenso_sensor.py
perception/exceptions.py
perception/kinect2_ros_sensor.py
perception/kinect2_sensor.py
perception/phoxi_sensor.py
perception/primesense_ros_sensor.py
perception/primesense_sensor.py
perception/realsense_sensor.py
perception/rgbd_sensors.py
perception/version.py
perception/video_recorder.py
perception/virtual_camera_sensor.py
perception/webcam_sensor.py
perception/weight_sensor.py
autolab_perception-1.0.0.dist-info/LICENSE
autolab_perception-1.0.0.dist-info/METADATA
autolab_perception-1.0.0.dist-info/WHEEL
autolab_perception-1.0.0.dist-info/top_level.txt
autolab_perception-1.0.0.dist-info/RECORD
