Metadata-Version: 2.1
Name: autolab-perception
Version: 1.0.0
Summary: Perception utilities for the Berkeley AutoLab
Home-page: https://github.com/BerkeleyAutomation/perception
Author: Jeff Mahler
Author-email: jmahler@berkeley.edu
Maintainer: Mike Danielczuk
Maintainer-email: mdanielczuk@berkeley.edu
License: Apache Software License
Keywords: robotics grasping vision perception
Platform: UNKNOWN
Classifier: Development Status :: 4 - Beta
Classifier: License :: OSI Approved :: Apache Software License
Classifier: Programming Language :: Python
Classifier: Programming Language :: Python :: 3.6
Classifier: Programming Language :: Python :: 3.7
Classifier: Programming Language :: Python :: 3.8
Classifier: Programming Language :: Python :: 3.9
Classifier: Natural Language :: English
Classifier: Topic :: Scientific/Engineering
Requires-Dist: numpy
Requires-Dist: scipy
Requires-Dist: autolab-core
Requires-Dist: opencv-python
Requires-Dist: pyserial (>=3.4)
Requires-Dist: ffmpeg-python
Provides-Extra: docs
Requires-Dist: sphinx ; extra == 'docs'
Requires-Dist: sphinxcontrib-napoleon ; extra == 'docs'
Requires-Dist: sphinx-rtd-theme ; extra == 'docs'
Provides-Extra: ros
Requires-Dist: primesense ; extra == 'ros'
Requires-Dist: rospkg ; extra == 'ros'
Requires-Dist: catkin-pkg ; extra == 'ros'
Requires-Dist: empy ; extra == 'ros'
